famapy/commands/__init__.py
famapy/core/__init__.py
famapy/core/config.py
famapy/core/discover.py
famapy/core/exceptions.py
famapy/core/plugins.py
famapy/core/utils.py
famapy/core/models/__init__.py
famapy/core/models/ast.py
famapy/core/models/variability_model.py
famapy/core/operations/__init__.py
famapy/core/operations/abstract_operation.py
famapy/core/operations/atomic_sets.py
famapy/core/operations/average_branching_factor.py
famapy/core/operations/commonality.py
famapy/core/operations/core_features.py
famapy/core/operations/count_leafs.py
famapy/core/operations/dead_features.py
famapy/core/operations/error_detection.py
famapy/core/operations/error_diagnosis.py
famapy/core/operations/estimated_products_number.py
famapy/core/operations/false_optional_features.py
famapy/core/operations/filter.py
famapy/core/operations/products.py
famapy/core/operations/products_number.py
famapy/core/operations/sampling.py
famapy/core/operations/valid.py
famapy/core/operations/valid_configuration.py
famapy/core/operations/valid_product.py
famapy/core/operations/variability.py
famapy/core/transformations/__init__.py
famapy/core/transformations/abstract_transformation.py
famapy/core/transformations/model_to_model.py
famapy/core/transformations/model_to_text.py
famapy/core/transformations/text_to_model.py
famapy/endpoint/diverso_lab.py
famapy/metamodels/configuration_metamodel/__init__.py
famapy/metamodels/configuration_metamodel/models/__init__.py
famapy/metamodels/configuration_metamodel/models/configuration.py
famapy/metamodels/configuration_metamodel/transformations/__init__.py
famapy/metamodels/configuration_metamodel/transformations/configuration_basic_reader.py
famapy-1.0.0.dist-info/METADATA
famapy-1.0.0.dist-info/WHEEL
famapy-1.0.0.dist-info/entry_points.txt
famapy-1.0.0.dist-info/top_level.txt
famapy-1.0.0.dist-info/RECORD
