Metadata-Version: 2.1
Name: famapy
Version: 1.0.0
Summary: FaMaPy is a Python-based AAFM framework that takes into consideration previous AAFM tool designs and enables multi-solver and multi-metamodel support for the integration of AAFM tooling on the Python ecosystem.
Home-page: https://github.com/FaMaPy/core
Author: Víctor Ramírez de la Corte
Author-email: me@virako.es
License: UNKNOWN
Platform: UNKNOWN
Classifier: Programming Language :: Python :: 3
Classifier: License :: OSI Approved :: GNU General Public License v3 or later (GPLv3+)
Classifier: Operating System :: OS Independent
Requires-Python: >=3.9
Requires-Dist: hug (>=2.6.1)
Provides-Extra: dev
Requires-Dist: pytest ; extra == 'dev'
Requires-Dist: pytest-mock ; extra == 'dev'
Requires-Dist: prospector ; extra == 'dev'
Requires-Dist: mypy ; extra == 'dev'
Requires-Dist: coverage ; extra == 'dev'
